{
  "btc": {
    "coingecko": {
      "historic": [
        {
          "timestamp": 12312312,
          "amount": 15.000
        }
      ],
      "markets": {
        "binance": {
          "usdt": {
            "url": "https://www.binance.com/en/trade/BTC_USDT?ref=H31B921U",
            "pair": "btc/usdt",
            "status": "ok|review|error|timeout|etc",
            "update_at": 1231312312
          }
        }
      },
      "alerts": {
        "telegram": {
          "status": "ok|error|lazy|timeout|etc",
          "exec_at": 12312312212312
        }
      },
      "status": "error|ok|partial|timeout|...",
      "update_at": 1231312312
    },
    "status": "error|ok|partial|timeout|..."
  }
}